setup.cfg
setup.py
falcon_middleware_beaker/__init__.py
falcon_middleware_beaker/utils.py
falcon_middleware_beaker/version.py
falcon_middleware_beaker.egg-info/PKG-INFO
falcon_middleware_beaker.egg-info/SOURCES.txt
falcon_middleware_beaker.egg-info/dependency_links.txt
falcon_middleware_beaker.egg-info/requires.txt
falcon_middleware_beaker.egg-info/top_level.txt