Metadata-Version: 1.1
Name: falcon-middleware-beaker
Version: 0.0.1
Summary: Beaker integration for falcon / hug
Home-page: https://github.com/gtxm/falcon_middleware_beaker
Author: Maciej Baranski
Author-email: maciej.baranski.gtxm@gmail.com
License: MIT
Keywords: Python,Python3,falcon,hug
Platform: UNKNOWN
Classifier: Development Status :: 3 - Alpha
Classifier: Intended Audience :: Developers
Classifier: Natural Language :: English
Classifier: License :: OSI Approved :: MIT License
Classifier: Programming Language :: Python
Classifier: Programming Language :: Python :: 3
Classifier: Programming Language :: Python :: 3.3
Classifier: Programming Language :: Python :: 3.4
Classifier: Programming Language :: Python :: 3.5
Classifier: Topic :: Software Development :: Libraries
Classifier: Topic :: Internet :: WWW/HTTP :: WSGI :: Middleware
Classifier: Topic :: Utilities
